authstar/__init__.py
authstar/fastapi.py
authstar/middleware.py
authstar/py.typed
authstar/types.py
authstar-0.0.6.dist-info/WHEEL
authstar-0.0.6.dist-info/METADATA
authstar-0.0.6.dist-info/RECORD
