Metadata-Version: 2.3
Name: authstar
Version: 0.0.6
Summary: Authstar ASGI Middleware for client authentication
Keywords: Authentication,ASGI
Author: John Wagenleitner
Author-email: John Wagenleitner <johnwa@mail.fresnostate.edu>
License:                                  Apache License
Classifier: Development Status :: 4 - Beta
Classifier: License :: OSI Approved :: Apache Software License
Classifier: Intended Audience :: Developers
Requires-Python: >=3.12, <3.15.0
Project-URL: Home, https://github.com/jowage58/authstar
Project-URL: Source, https://github.com/jowage58/authstar
